toolcase/README.md
toolcase/__init__.py
toolcase/py.typed
toolcase/cli/__init__.py
toolcase/cli/help.py
toolcase/cli/topics/__init__.py
toolcase/cli/topics/agents.py
toolcase/cli/topics/architecture.py
toolcase/cli/topics/batch.py
toolcase/cli/topics/cache.py
toolcase/cli/topics/capabilities.py
toolcase/cli/topics/concurrency.py
toolcase/cli/topics/di.py
toolcase/cli/topics/discovery.py
toolcase/cli/topics/dlq.py
toolcase/cli/topics/effects.py
toolcase/cli/topics/errors.py
toolcase/cli/topics/events.py
toolcase/cli/topics/fast.py
toolcase/cli/topics/formats.py
toolcase/cli/topics/help_topic.py
toolcase/cli/topics/http.py
toolcase/cli/topics/imports.py
toolcase/cli/topics/logging.py
toolcase/cli/topics/mcp.py
toolcase/cli/topics/middleware.py
toolcase/cli/topics/overview.py
toolcase/cli/topics/pipeline.py
toolcase/cli/topics/quickstart.py
toolcase/cli/topics/registry.py
toolcase/cli/topics/resilience.py
toolcase/cli/topics/result.py
toolcase/cli/topics/retry.py
toolcase/cli/topics/settings.py
toolcase/cli/topics/streaming.py
toolcase/cli/topics/testing.py
toolcase/cli/topics/tool.py
toolcase/cli/topics/tracing.py
toolcase/cli/topics/validation.py
toolcase/cli/topics/web.py
toolcase/dev/README.md
toolcase/dev/__init__.py
toolcase/dev/tests/test_agents.py
toolcase/dev/tests/test_batch.py
toolcase/dev/tests/test_cache.py
toolcase/dev/tests/test_coalesce.py
toolcase/dev/tests/test_di.py
toolcase/dev/tests/test_effects.py
toolcase/dev/tests/test_fast.py
toolcase/dev/tests/test_http_tool.py
toolcase/dev/tests/test_pipeline_streaming.py
toolcase/dev/tests/test_result.py
toolcase/dev/tests/test_result_streaming.py
toolcase/dev/tests/test_rules.py
toolcase/dev/tests/test_strategy.py
toolcase/dev/tests/test_streaming.py
toolcase/dev/tests/test_testing.py
toolcase/examples/__init__.py
toolcase/examples/web_research_agent.py
toolcase/ext/README.md
toolcase/ext/__init__.py
toolcase/ext/integrations/__init__.py
toolcase/ext/integrations/frontiers.py
toolcase-0.1.0.dist-info/METADATA
toolcase-0.1.0.dist-info/WHEEL
toolcase-0.1.0.dist-info/entry_points.txt
toolcase-0.1.0.dist-info/licenses/LICENSE
toolcase-0.1.0.dist-info/RECORD
