Metadata-Version: 2.4
Name: toolcase
Version: 0.1.0
Summary: Type-safe, extensible tool framework for AI agents with monadic error handling
Author-email: GriffinCanCode <griffincancode@gmail.com>
License:                 ╔══════════════════════════════════════════════════════════════════════════════╗
License-File: LICENSE
Keywords: agents,ai,langchain,llm,mcp,model-context-protocol,tools
Classifier: Development Status :: 4 - Beta
Classifier: Intended Audience :: Developers
Classifier: License :: Other/Proprietary License
Classifier: Programming Language :: Python :: 3
Classifier: Programming Language :: Python :: 3.11
Classifier: Programming Language :: Python :: 3.12
Classifier: Programming Language :: Python :: 3.13
Classifier: Typing :: Typed
Requires-Python: >=3.11
Requires-Dist: beartype>=0.18
Requires-Dist: httpx>=0.27
Requires-Dist: msgpack>=1.0
Requires-Dist: msgspec>=0.18
Requires-Dist: orjson>=3.9
Requires-Dist: pydantic-extra-types>=2.6
Requires-Dist: pydantic-settings>=2.2
Requires-Dist: pydantic>=2.7
Requires-Dist: stamina>=24.3
Requires-Dist: structlog>=24.1
Provides-Extra: all
Requires-Dist: fastmcp>=2.0; extra == 'all'
Requires-Dist: langchain-core>=0.2; extra == 'all'
Requires-Dist: opentelemetry-api>=1.20; extra == 'all'
Requires-Dist: opentelemetry-exporter-otlp-proto-grpc>=1.20; extra == 'all'
Requires-Dist: opentelemetry-exporter-otlp-proto-http>=1.20; extra == 'all'
Requires-Dist: opentelemetry-instrumentation-httpx>=0.42b0; extra == 'all'
Requires-Dist: opentelemetry-sdk>=1.20; extra == 'all'
Requires-Dist: pymemcache>=4.0; extra == 'all'
Requires-Dist: redis>=5.0; extra == 'all'
Requires-Dist: starlette>=0.37; extra == 'all'
Requires-Dist: uvicorn>=0.29; extra == 'all'
Provides-Extra: dev
Requires-Dist: hypothesis>=6.100; extra == 'dev'
Requires-Dist: mypy>=1.10; extra == 'dev'
Requires-Dist: pytest-asyncio>=0.23; extra == 'dev'
Requires-Dist: pytest>=8.0; extra == 'dev'
Requires-Dist: ruff>=0.4; extra == 'dev'
Provides-Extra: http
Requires-Dist: starlette>=0.37; extra == 'http'
Requires-Dist: uvicorn>=0.29; extra == 'http'
Provides-Extra: langchain
Requires-Dist: langchain-core>=0.2; extra == 'langchain'
Provides-Extra: mcp
Requires-Dist: fastmcp>=2.0; extra == 'mcp'
Provides-Extra: memcached
Requires-Dist: pymemcache>=4.0; extra == 'memcached'
Provides-Extra: otel
Requires-Dist: opentelemetry-api>=1.20; extra == 'otel'
Requires-Dist: opentelemetry-exporter-otlp-proto-grpc>=1.20; extra == 'otel'
Requires-Dist: opentelemetry-exporter-otlp-proto-http>=1.20; extra == 'otel'
Requires-Dist: opentelemetry-instrumentation-httpx>=0.42b0; extra == 'otel'
Requires-Dist: opentelemetry-sdk>=1.20; extra == 'otel'
Provides-Extra: redis
Requires-Dist: redis>=5.0; extra == 'redis'
